tkmap/__init__.py
tkmap/concurrency/__init__.py
tkmap/events.py
tkmap/layers/__init__.py
tkmap/layers/geojson.py
tkmap/layers/layer.py
tkmap/layers/tile.py
tkmap/map_widget.py
tkmap/model.py
tkmap/tileloaders/__init__.py
tkmap/tileloaders/base.py
tkmap/tileloaders/default.py
tkmap/tileloaders/disk_cache.py
tkmap/tileloaders/error_cache.py
tkmap/tileloaders/logging_tile_loader.py
tkmap/tileloaders/memory_cache.py
tkmap/tileloaders/remote.py
tkmap/viewport.py
tkmap-0.1.2.dist-info/METADATA
tkmap-0.1.2.dist-info/WHEEL
tkmap-0.1.2.dist-info/RECORD
