Metadata-Version: 2.3
Name: tkmap
Version: 0.1.2
Summary: A simple tkinter map widget
License: Apache-2.0
Author: Curtis Ruck
Requires-Python: >=3.10
Classifier: License :: OSI Approved :: Apache Software License
Classifier: Programming Language :: Python :: 3
Classifier: Programming Language :: Python :: 3.10
Classifier: Programming Language :: Python :: 3.11
Classifier: Programming Language :: Python :: 3.12
Classifier: Programming Language :: Python :: 3.13
Requires-Dist: geojson (>=3.2.0,<4.0.0)
Requires-Dist: pillow (>=11,<12.0.0)
Requires-Dist: requests (>=2.27.0,<3.0.0)
Project-URL: Issues, https://github.com/ruckc/tkmap/issues
Project-URL: Repository, https://github.com/ruckc/tkmap
